pyADMETPredictor/__init__.py
pyADMETPredictor/_version.py
pyADMETPredictor/pyADMETPredictorHelper.py
pyADMETPredictor/pyADMETPredictorWrapper.py
pyADMETPredictor/config/REST/launchAPservice13.bat
pyadmetpredictor-0.2.1.dist-info/licenses/LICENSE
pyadmetpredictor-0.2.1.dist-info/METADATA
pyadmetpredictor-0.2.1.dist-info/WHEEL
pyadmetpredictor-0.2.1.dist-info/top_level.txt
pyadmetpredictor-0.2.1.dist-info/RECORD
