Metadata-Version: 2.4
Name: pyADMETPredictor
Version: 0.2.1
Author-email: "Rafal A. Bachorz" <rafal.bachorz@simulations-plus.com>
License: LGPL-3.0
Project-URL: homepage, https://bitbucket.org/slp-cheminformatics/pyadmetpredictor
Project-URL: repository, https://bitbucket.org/slp-cheminformatics/pyadmetpredictor
Keywords: Simulations Plus,ADMET Predictor,qsar,qspr,integration
Classifier: Development Status :: 4 - Beta
Classifier: Intended Audience :: Science/Research
Classifier: Intended Audience :: Healthcare Industry
Classifier: License :: OSI Approved :: GNU General Public License v3 (GPLv3)
Classifier: Programming Language :: Python
Classifier: Programming Language :: Python :: 3 :: Only
Classifier: Programming Language :: Python :: 3.9
Classifier: Programming Language :: Python :: 3.10
Classifier: Programming Language :: Python :: 3.11
Classifier: Programming Language :: Python :: 3.12
Classifier: Topic :: Scientific/Engineering
Classifier: Topic :: Scientific/Engineering :: Bio-Informatics
Classifier: Topic :: Scientific/Engineering :: Chemistry
Classifier: Topic :: Utilities
Classifier: Operating System :: Microsoft :: Windows
Classifier: Operating System :: POSIX
Classifier: Operating System :: Unix
Classifier: Operating System :: MacOS
Requires-Python: >=3.7
License-File: LICENSE
Requires-Dist: requests>=2.31.0
Requires-Dist: pandas>=2.1.0
Requires-Dist: rdkit>=2024.3.3
Provides-Extra: dev
Requires-Dist: pytest>=6; extra == "dev"
Requires-Dist: pytest-cov; extra == "dev"
Requires-Dist: pytest-timeout; extra == "dev"
Requires-Dist: pytest-xdist; extra == "dev"
Requires-Dist: pytest-asyncio; extra == "dev"
Requires-Dist: twine; extra == "dev"
Provides-Extra: notebook
Requires-Dist: ipywidgets>=6; extra == "notebook"
Dynamic: license-file
